{
  "generated_at": "2026-04-28T22:51:58.527658+00:00",
  "video_alerts": 206,
  "channel_alerts": 78,
  "data_quality_alerts": 0,
  "total_alerts": 284,
  "severity_counts": {
    "critical": 11,
    "high": 68,
    "medium": 199,
    "low": 6
  },
  "signal_type_counts": {
    "channel_high_growth": 22,
    "channel_volatility_warning": 31,
    "accelerating_video": 10,
    "metadata_change_watch": 7,
    "high_engagement_low_reach": 102,
    "packaging_problem": 68,
    "channel_momentum_up": 17,
    "trend_burst": 19,
    "channel_consistent_performer": 8
  },
  "top_alerts": [
    {
      "alert_id": "alrt_832ceae3d586beda",
      "execution_date": "2026-04-28T22:50:38.290626+00:00",
      "generated_at": "2026-04-28T22:51:58.527658+00:00",
      "entity_type": "channel",
      "entity_id": "UCLe_q9axMaeTbjN0hy1Z9xA",
      "video_id": "",
      "channel_id": "UCLe_q9axMaeTbjN0hy1Z9xA",
      "channel_name": "Caleb Hammer",
      "title": "",
      "signal_type": "channel_high_growth",
      "severity": "critical",
      "raw_signal_score": 100.0,
      "adjusted_signal_score": 100.0,
      "metric_confidence_score": 100.0,
      "confidence_level": "high",
      "message": "Señal de canal detectada: channel_high_growth.",
      "evidence_json": {
        "threshold": 80.0,
        "raw_signal_score": 100.0,
        "metric_confidence_score": 100.0
      },
      "recommended_action": "Canal dominante en crecimiento; revisar estrategia.",
      "dashboard_tab": "Channels",
      "source_tables": [
        "latest_channel_advanced_metrics.csv",
        "latest_channel_metrics.csv"
      ]
    },
    {
      "alert_id": "alrt_e245ac5251a566c3",
      "execution_date": "2026-04-28T22:50:38.290626+00:00",
      "generated_at": "2026-04-28T22:51:58.527658+00:00",
      "entity_type": "channel",
      "entity_id": "UCF0L4jd9LcSIxsj5gKITMqQ",
      "video_id": "",
      "channel_id": "UCF0L4jd9LcSIxsj5gKITMqQ",
      "channel_name": "Jaime Higuera",
      "title": "",
      "signal_type": "channel_volatility_warning",
      "severity": "critical",
      "raw_signal_score": 99.0,
      "adjusted_signal_score": 99.0,
      "metric_confidence_score": 100.0,
      "confidence_level": "high",
      "message": "Señal de canal detectada: channel_volatility_warning.",
      "evidence_json": {
        "threshold": 30.0,
        "raw_signal_score": 99.0,
        "metric_confidence_score": 100.0
      },
      "recommended_action": "Interpretar señales del canal con cautela por alta volatilidad.",
      "dashboard_tab": "Channels",
      "source_tables": [
        "latest_channel_advanced_metrics.csv",
        "latest_channel_metrics.csv"
      ]
    },
    {
      "alert_id": "alrt_2f6a1b82105b3376",
      "execution_date": "2026-04-28T22:50:38.290626+00:00",
      "generated_at": "2026-04-28T22:51:58.527658+00:00",
      "entity_type": "channel",
      "entity_id": "UCWBWgCD4oAqT3hUeq40SCUw",
      "video_id": "",
      "channel_id": "UCWBWgCD4oAqT3hUeq40SCUw",
      "channel_name": "Sambucha",
      "title": "",
      "signal_type": "channel_high_growth",
      "severity": "critical",
      "raw_signal_score": 98.0952,
      "adjusted_signal_score": 96.3786,
      "metric_confidence_score": 96.5,
      "confidence_level": "high",
      "message": "Señal de canal detectada: channel_high_growth.",
      "evidence_json": {
        "threshold": 80.0,
        "raw_signal_score": 98.0952,
        "metric_confidence_score": 96.5
      },
      "recommended_action": "Canal dominante en crecimiento; revisar estrategia.",
      "dashboard_tab": "Channels",
      "source_tables": [
        "latest_channel_advanced_metrics.csv",
        "latest_channel_metrics.csv"
      ]
    },
    {
      "alert_id": "alrt_a5f5dd0e6a9eb6f0",
      "execution_date": "2026-04-28T22:50:38.290626+00:00",
      "generated_at": "2026-04-28T22:51:58.527658+00:00",
      "entity_type": "channel",
      "entity_id": "UCjSVqRtdOsxQDss_pJpp_Yg",
      "video_id": "",
      "channel_id": "UCjSVqRtdOsxQDss_pJpp_Yg",
      "channel_name": "COMPUESTOS Podcast",
      "title": "",
      "signal_type": "channel_volatility_warning",
      "severity": "critical",
      "raw_signal_score": 97.0,
      "adjusted_signal_score": 96.1512,
      "metric_confidence_score": 98.25,
      "confidence_level": "high",
      "message": "Señal de canal detectada: channel_volatility_warning.",
      "evidence_json": {
        "threshold": 30.0,
        "raw_signal_score": 97.0,
        "metric_confidence_score": 98.25
      },
      "recommended_action": "Interpretar señales del canal con cautela por alta volatilidad.",
      "dashboard_tab": "Channels",
      "source_tables": [
        "latest_channel_advanced_metrics.csv",
        "latest_channel_metrics.csv"
      ]
    },
    {
      "alert_id": "alrt_edf7b05b461c2da2",
      "execution_date": "2026-04-28T22:50:38.290626+00:00",
      "generated_at": "2026-04-28T22:51:58.527658+00:00",
      "entity_type": "channel",
      "entity_id": "UCl5-lvQyfILb-l2abPk4Ntg",
      "video_id": "",
      "channel_id": "UCl5-lvQyfILb-l2abPk4Ntg",
      "channel_name": "Inteligencia Artificial",
      "title": "",
      "signal_type": "channel_volatility_warning",
      "severity": "critical",
      "raw_signal_score": 96.0,
      "adjusted_signal_score": 96.0,
      "metric_confidence_score": 100.0,
      "confidence_level": "high",
      "message": "Señal de canal detectada: channel_volatility_warning.",
      "evidence_json": {
        "threshold": 30.0,
        "raw_signal_score": 96.0,
        "metric_confidence_score": 100.0
      },
      "recommended_action": "Interpretar señales del canal con cautela por alta volatilidad.",
      "dashboard_tab": "Channels",
      "source_tables": [
        "latest_channel_advanced_metrics.csv",
        "latest_channel_metrics.csv"
      ]
    },
    {
      "alert_id": "alrt_2a9a75d5d5ca0abd",
      "execution_date": "2026-04-28T22:50:38.290626+00:00",
      "generated_at": "2026-04-28T22:51:58.527658+00:00",
      "entity_type": "channel",
      "entity_id": "UCUyDOdBWhC1MCxEjC46d-zw",
      "video_id": "",
      "channel_id": "UCUyDOdBWhC1MCxEjC46d-zw",
      "channel_name": "Alex Hormozi",
      "title": "",
      "signal_type": "channel_volatility_warning",
      "severity": "critical",
      "raw_signal_score": 94.0,
      "adjusted_signal_score": 94.0,
      "metric_confidence_score": 100.0,
      "confidence_level": "high",
      "message": "Señal de canal detectada: channel_volatility_warning.",
      "evidence_json": {
        "threshold": 30.0,
        "raw_signal_score": 94.0,
        "metric_confidence_score": 100.0
      },
      "recommended_action": "Interpretar señales del canal con cautela por alta volatilidad.",
      "dashboard_tab": "Channels",
      "source_tables": [
        "latest_channel_advanced_metrics.csv",
        "latest_channel_metrics.csv"
      ]
    },
    {
      "alert_id": "alrt_0d95a9773f8636d9",
      "execution_date": "2026-04-28T22:50:38.290626+00:00",
      "generated_at": "2026-04-28T22:51:58.527658+00:00",
      "entity_type": "channel",
      "entity_id": "UCUyDOdBWhC1MCxEjC46d-zw",
      "video_id": "",
      "channel_id": "UCUyDOdBWhC1MCxEjC46d-zw",
      "channel_name": "Alex Hormozi",
      "title": "",
      "signal_type": "channel_high_growth",
      "severity": "critical",
      "raw_signal_score": 93.3333,
      "adjusted_signal_score": 93.3333,
      "metric_confidence_score": 100.0,
      "confidence_level": "high",
      "message": "Señal de canal detectada: channel_high_growth.",
      "evidence_json": {
        "threshold": 80.0,
        "raw_signal_score": 93.3333,
        "metric_confidence_score": 100.0
      },
      "recommended_action": "Canal dominante en crecimiento; revisar estrategia.",
      "dashboard_tab": "Channels",
      "source_tables": [
        "latest_channel_advanced_metrics.csv",
        "latest_channel_metrics.csv"
      ]
    },
    {
      "alert_id": "alrt_efb6f071a5f446de",
      "execution_date": "2026-04-28T22:50:38.290626+00:00",
      "generated_at": "2026-04-28T22:51:58.527658+00:00",
      "entity_type": "channel",
      "entity_id": "UCbUYAYd1WUznxEEl498z7vA",
      "video_id": "",
      "channel_id": "UCbUYAYd1WUznxEEl498z7vA",
      "channel_name": "Woshingo Streams",
      "title": "",
      "signal_type": "channel_volatility_warning",
      "severity": "critical",
      "raw_signal_score": 100.0,
      "adjusted_signal_score": 91.25,
      "metric_confidence_score": 82.5,
      "confidence_level": "high",
      "message": "Señal de canal detectada: channel_volatility_warning.",
      "evidence_json": {
        "threshold": 30.0,
        "raw_signal_score": 100.0,
        "metric_confidence_score": 82.5
      },
      "recommended_action": "Interpretar señales del canal con cautela por alta volatilidad.",
      "dashboard_tab": "Channels",
      "source_tables": [
        "latest_channel_advanced_metrics.csv",
        "latest_channel_metrics.csv"
      ]
    },
    {
      "alert_id": "alrt_7ea421ae47b9b88f",
      "execution_date": "2026-04-28T22:50:38.290626+00:00",
      "generated_at": "2026-04-28T22:51:58.527658+00:00",
      "entity_type": "channel",
      "entity_id": "UCQHX6ViZmPsWiYSFAyS0a3Q",
      "video_id": "",
      "channel_id": "UCQHX6ViZmPsWiYSFAyS0a3Q",
      "channel_name": "GothamChess",
      "title": "",
      "signal_type": "channel_high_growth",
      "severity": "critical",
      "raw_signal_score": 96.1905,
      "adjusted_signal_score": 91.1405,
      "metric_confidence_score": 89.5,
      "confidence_level": "high",
      "message": "Señal de canal detectada: channel_high_growth.",
      "evidence_json": {
        "threshold": 80.0,
        "raw_signal_score": 96.1905,
        "metric_confidence_score": 89.5
      },
      "recommended_action": "Canal dominante en crecimiento; revisar estrategia.",
      "dashboard_tab": "Channels",
      "source_tables": [
        "latest_channel_advanced_metrics.csv",
        "latest_channel_metrics.csv"
      ]
    },
    {
      "alert_id": "alrt_d90bba293d6e1c83",
      "execution_date": "2026-04-28T22:50:38.290626+00:00",
      "generated_at": "2026-04-28T22:51:58.527658+00:00",
      "entity_type": "channel",
      "entity_id": "UC5mQQ4Ur6oA8lsGFkvH2lyg",
      "video_id": "",
      "channel_id": "UC5mQQ4Ur6oA8lsGFkvH2lyg",
      "channel_name": "Noche De Chicxs",
      "title": "",
      "signal_type": "channel_volatility_warning",
      "severity": "critical",
      "raw_signal_score": 93.0,
      "adjusted_signal_score": 90.5588,
      "metric_confidence_score": 94.75,
      "confidence_level": "high",
      "message": "Señal de canal detectada: channel_volatility_warning.",
      "evidence_json": {
        "threshold": 30.0,
        "raw_signal_score": 93.0,
        "metric_confidence_score": 94.75
      },
      "recommended_action": "Interpretar señales del canal con cautela por alta volatilidad.",
      "dashboard_tab": "Channels",
      "source_tables": [
        "latest_channel_advanced_metrics.csv",
        "latest_channel_metrics.csv"
      ]
    }
  ],
  "warnings": []
}